[
  {
    "id": 1,
    "challenge": "learn Http test",
    "startDate": "2025-02-03",
    "status": "pending",
    "createdBy": "Ahmed",
    "updatedBy": "reda"
  },
  {
    "challenge": "learn Http test",
    "startDate": "2025-02-03",
    "status": "pending",
    "createdBy": "Ahmed",
    "updatedBy": "abdellhay",
    "id": 2
  },
  {
    "challenge": "learn Http test",
    "startDate": "2025-02-03",
    "status": "pending",
    "createdBy": "Ahmed",
    "updatedBy": "reda",
    "id": 4
  },
  {
    "challenge": "learn Http test",
    "startDate": "2025-02-03",
    "status": "pending",
    "createdBy": "abdellhay",
    "id": 5
  }
]